topsis/__init__.py
topsis/topsis.py
topsis_mansehaj_102303544-1.0.0.dist-info/METADATA
topsis_mansehaj_102303544-1.0.0.dist-info/WHEEL
topsis_mansehaj_102303544-1.0.0.dist-info/entry_points.txt
topsis_mansehaj_102303544-1.0.0.dist-info/top_level.txt
topsis_mansehaj_102303544-1.0.0.dist-info/RECORD
