Metadata-Version: 2.4
Name: topsis-Mansehaj-102303544
Version: 1.0.0
Summary: TOPSIS implementation as a Python package
Author: Mansehaj
Requires-Dist: pandas
Requires-Dist: numpy
Dynamic: author
Dynamic: requires-dist
Dynamic: summary
